ducat/__init__.py
ducat/adb.py
ducat/confloader.py
ducat/helper.py
ducat/logfile_parser.py
ducat/logprocessor.py
ducat/logregex.py
ducat/logseparator.py
ducat/terminalcolor.py
ducat/trans.py
DuCat-1.0.1.dist-info/LICENSE.txt
DuCat-1.0.1.dist-info/METADATA
DuCat-1.0.1.dist-info/WHEEL
DuCat-1.0.1.dist-info/entry_points.txt
DuCat-1.0.1.dist-info/top_level.txt
DuCat-1.0.1.dist-info/RECORD
